s3toecs.py
setup.cfg
setup.py
S3toECS.egg-info/PKG-INFO
S3toECS.egg-info/SOURCES.txt
S3toECS.egg-info/dependency_links.txt
S3toECS.egg-info/entry_points.txt
S3toECS.egg-info/top_level.txt