Metadata-Version: 1.2
Name: S3toECS
Version: 0.1.4
Summary: Tool that transfers Docker images from S3 to your ECS repository.
Home-page: https://github.com/territory-webguerillas/s3toecs/
Author: Antonio Maiolo
Author-email: maiolo.antonio@territory.de
License: MIT License
Download-URL: https://github.com/territory-webguerillas/s3toecs/archive/0.1.4.tar.gz
Keywords: s3,ecs,aws,s3 to ecs
Platform: UNKNOWN
Classifier: Environment :: Console
Classifier: Intended Audience :: Developers
Classifier: License :: OSI Approved :: MIT License
Classifier: Programming Language :: Python
Classifier: Programming Language :: Python :: 3.6
Requires-Python: >=3.6
